mkdesigner/__init__.py
mkdesigner/addprimertovcf.py
mkdesigner/haplocall.py
mkdesigner/mergevcf.py
mkdesigner/mkprimer.py
mkdesigner/mkselect.py
mkdesigner/mkvcf.py
mkdesigner/mvinputfiles.py
mkdesigner/params.py
mkdesigner/refindex.py
mkdesigner/removetoolargeindel.py
mkdesigner/selectvariants.py
mkdesigner/utils.py
mkdesigner/visualize_marker.py
mkdesigner-0.5.2.dist-info/LICENSE
mkdesigner-0.5.2.dist-info/METADATA
mkdesigner-0.5.2.dist-info/WHEEL
mkdesigner-0.5.2.dist-info/entry_points.txt
mkdesigner-0.5.2.dist-info/top_level.txt
mkdesigner-0.5.2.dist-info/RECORD
