Metadata-Version: 2.2
Name: mkdesigner
Version: 0.5.2
Summary: Genome-wide design of markers for PCR-based genotyping from NGS data.
Home-page: https://github.com/KChigira/mkdesigner/
Author: Koki Chigira
Author-email: kyoujin2009kutar@gmail.com
License: MIT
License-File: LICENSE
Requires-Dist: pandas
Requires-Dist: matplotlib
Requires-Dist: timeout-decorator
Dynamic: author
Dynamic: author-email
Dynamic: home-page
Dynamic: license
Dynamic: requires-dist
Dynamic: summary
